[
  {
    "id": 1,
    "items": [
      {
        "term": "Boynun",
        "match": "orta sisti yaranır:->Tiroqlossal uğramamasından",
        "incorrect": []
      },
      {
        "term": "Boynun yan sistləri yaranır",
        "match": "İkinci bronxial qövsdən",
        "incorrect": [
          "Birinci bronxial qövsdən",
          "Üçüncü bronxial qövsdən",
          "Dilaltı sümüyünün inkişaf qüsuru nəticəsində"
        ]
      }
    ]
  },
  {
    "id": 2,
    "items": [
      {
        "term": null,
        "match": null,
        "incorrect": [
          "yolun oblterasiyaya"
        ]
      },
      {
        "term": "Ağciyər absesi",
        "match": "Ağciyərdə iltihabi infiltrativ sahə və irinli eksudat.",
        "incorrect": []
      },
      {
        "term": "Pnevmotosele",
        "match": "Ağciyərdə olan nazik divarlı havalı boşluq",
        "incorrect": [
          "Plevra boşluğuna hava və irinin toplanması",
          "Plevra boşluğuna irinli eksudatın toplanması",
          "Ağciyərin payının total irinli infiltrasiyası"
        ]
      }
    ]
  },
  {
    "id": 3,
    "items": [
      {
        "term": "İrinli lobit",
        "match": "Ağciyər payının total tündləşməsi və reaktiv plevrit.",
        "incorrect": []
      },
      {
        "term": "Ağciyər absesi",
        "match": "Dairəvi formalı, aydın sərhədlərə malik, bəzən içərisində maye səviyyəsi və üzərində hava olan kölgəlik. tündləşmə, diafraqma gümbəzinin və plevral sinusun ayrıd edilməməsi. ağciyər toxumasında olan müxtəlif ölçülü nazik divarlı havalı boşluqlar. aydın sərhədləri üzərində olması, ürək kölgəliyinin əks tərəfə yerini dəyişməsi.",
        "incorrect": [
          "Divararalığı əks tərəfə yerini dəyişməklə döş qəfəsinin zədələnən yarısında",
          "Dəyişikliyə uğramış",
          "Plevra boşluğunda horizontal maye səviyyəsi"
        ]
      }
    ]
  },
  {
    "id": 4,
    "items": [
      {
        "term": null,
        "match": "Ağciyərin hipoplaziyası:-> Çoxsaylı havanın sistoz genişlənmələr fonunda ağciyərin respirator sahələrinin inkişafdan qalması.",
        "incorrect": []
      },
      {
        "term": "Ağciyərin aplaziyası",
        "match": "Rudimentar baş bronxun olması, olmaması. ağciyərin izoləolunmuş, sistoz dəyişikli olması",
        "incorrect": [
          "Ağciyərin paylarından birinin kəskin böyüyərək havalılığının artması.",
          "Ağciyərin və baş bronxun olmaması.",
          "Ağciyərin bir hissəsinin anomal damarla qidalanan bronx sistemindən"
        ]
      }
    ]
  },
  {
    "id": 5,
    "items": [
      {
        "term": "12 barmaq bağırsağın anadangəlmə keçməzliyi",
        "match": "İki maye səviyyəsi və bağırsaqlarda qazın olmaması.",
        "incorrect": []
      },
      {
        "term": "Nazik bağırsağın anadangəlmə keçməzliyi",
        "match": "Bir neçə maye səviyyəsinin olması və bu səviyyələrdən aşağıda qazın olmaması müayinədə kor bağırsağın yuxarı və medial yerləşməsi. ilgəklərində çoxlu sayda maye səviyyələrinin olması. saatadək ləngiməsi.",
        "incorrect": [
          "İki maye səviyyəsi və bağırsaqların zəif şəkildə qazla dolması, kontrast rentgen",
          "Genişlənmiş bağırsaq",
          "Genişlənmiş mədədə"
        ]
      }
    ]
  },
  {
    "id": 6,
    "items": [
      {
        "term": "Mekkel",
        "match": "divertikulu:-> kontrast Yumurta maddənin 3 sarısı-bağırsaq saatdan axacağının proksimal hissəsinin obliterasiya prosesinin pozulması nəticəsində yaranır.",
        "incorrect": []
      },
      {
        "term": "Göbəyin tam fistulu",
        "match": "Yumurta sarısı-bağırsaq axacağının tam olaraq obliterasiya prosesinin pozulması nəticəsində yaranır. axacağın prosesinin pozulması nəticəsində yaranır distal hissəsinin obliterasiya 24 pozulması nəticəsində yaranır.",
        "incorrect": [
          "Yumurta sarısı-bağırsaq",
          "Yumurta sarısı-bağırsaq axacağın orta hissəsinin obliterasiya prosesinin",
          "Nazik bağırsağın damar qəzaları nəticəsində yaranır."
        ]
      }
    ]
  },
  {
    "id": 7,
    "items": [
      {
        "term": "Axalaziya",
        "match": "Qida borusunun kardial hissəsinin daralması.",
        "incorrect": []
      },
      {
        "term": "Pilorostenoz",
        "match": "Mədənin pilorik hissəsinin daralması. =->Qida borusunun kardial hissəsnin çatışmazlığı =->Mədənin pilorik hissəsinin atreziyası.",
        "incorrect": [
          "Diafraqmanın qida borusu dəliyinin yırtığı"
        ]
      }
    ]
  },
  {
    "id": 8,
    "items": [
      {
        "term": "Mekkel divertikulunaxarakterdir",
        "match": "Həzm sistemindən qanaxma.",
        "incorrect": []
      },
      {
        "term": "Uraxus fistulasına xarakterdir",
        "match": "Göbəyin daim islanması.",
        "incorrect": [
          "Qanlı sidik ifrazı.",
          "Göbəkdən nəcis ifrazı.",
          "Qanlı qusma"
        ]
      }
    ]
  },
  {
    "id": 9,
    "items": [
      {
        "term": null,
        "match": null,
        "incorrect": [
          "Uyğunluğu müəyyən edin."
        ]
      },
      {
        "term": "Embriogenez dövründə bagırsağın normal fırlanma prosesinin pozulması",
        "match": "nəticəsində əmələ gəlir:- ˃Ledd sindromu",
        "incorrect": []
      },
      {
        "term": "«Xarici tipli» anadangəlmə bağırsaq keşməzliyi",
        "match": "Nalvari mədəaltı vəzi",
        "incorrect": [
          "Hirşprunq xəstəliyi",
          "Kəskin bağırsaq invaqinasiyası",
          "Pyer-Roben sindromu"
        ]
      }
    ]
  },
  {
    "id": 10,
    "items": [
      {
        "term": null,
        "match": null,
        "incorrect": [
          "Uyğunluğu müəyyən edin."
        ]
      },
      {
        "term": "Bağırsağın bir hissəsinin o biri hissəsinin içərisinə keçib pərçim",
        "match": "olunması: - ˃İnvaqinasiya",
        "incorrect": []
      },
      {
        "term": "Qalça bağırsağının mənfəzinin «İlk nəcislə» obturasiya olunması -",
        "match": "Mekoneal ileus",
        "incorrect": [
          "Nəcis daşı",
          "Orta bağırsaq burulması",
          "Peyts-Egerts sindromu"
        ]
      }
    ]
  },
  {
    "id": 11,
    "items": [
      {
        "term": null,
        "match": null,
        "incorrect": [
          "Uyğunluğu müəyyən edin."
        ]
      },
      {
        "term": "Öd qarışığı olmadan «fəvvarə» şəklində qusma",
        "match": "Pilorostenoz",
        "incorrect": []
      },
      {
        "term": "Doğularkən uşaqda ağız və burun dəliklərindən köpüklü ifrazatın xaric",
        "match": "olunması -˃Yemək borusunun atreziyası",
        "incorrect": [
          "Pilorospazm",
          "Yemək borusunu axalaziyası",
          "Paralitik bağırsaq keşməzliyi"
        ]
      }
    ]
  },
  {
    "id": 12,
    "items": [
      {
        "term": null,
        "match": null,
        "incorrect": [
          "Uyğunluğu müəyyən edin."
        ]
      },
      {
        "term": "Obturasion bağırsaq keşməzliyinin növü",
        "match": "Koprostaz",
        "incorrect": []
      },
      {
        "term": "Stranqulyasion bağırsaq keşməzliyinin növü",
        "match": "Birləşmə məşəlibağırsaq keşməzliyi",
        "incorrect": [
          "Enkoprez",
          "Ekzostoz",
          "Pertes xəstəliyi"
        ]
      }
    ]
  },
  {
    "id": 13,
    "items": [
      {
        "term": null,
        "match": null,
        "incorrect": [
          "Uyğunluğu müəyyən edin."
        ]
      },
      {
        "term": "Hirşprunq xəstəliyinin diqnostiksında işlənən kontrast rengenolojı müayinə",
        "match": "üsulu:- ˃ İrriqoqrafiya",
        "incorrect": []
      },
      {
        "term": "Düz bağısağın atreziyası zamanı işlənən rengenolojı müayinə üsulu",
        "match": "Vangenstin üsulu",
        "incorrect": [
          "Kolonoskopiya",
          "Dühamel-Bairov üsulu",
          "Rektal müayinəsi"
        ]
      }
    ]
  },
  {
    "id": 14,
    "items": []
  },
  {
    "id": 15,
    "items": [
      {
        "term": null,
        "match": null,
        "incorrect": [
          "Uyğunluğu müəyyən edin."
        ]
      },
      {
        "term": "Köks qəfəsinin inkişaf qüsurlarına aidolan deformasiya",
        "match": "«Qıfvari»",
        "incorrect": []
      },
      {
        "term": "Döş sümüyünün deformasiyalarına aid olan formalardan biri",
        "match": null,
        "incorrect": [
          "Yastı",
          "Qayıqvari",
          "Kifoz"
        ]
      }
    ]
  },
  {
    "id": 16,
    "items": [
      {
        "term": null,
        "match": null,
        "incorrect": [
          "Uyğunluğu müəyyən edin."
        ]
      },
      {
        "term": "Ağciyərlərin ən şox rast gəlinən parazitar sistləri",
        "match": "Exinikokk sisti",
        "incorrect": []
      },
      {
        "term": "Anadangəlmə ağciyər sistlərinə aiddir",
        "match": "Bronxogen sist",
        "incorrect": [
          "Enterosistoma",
          "Vilms şişi",
          "Dermoid sisti"
        ]
      }
    ]
  },
  {
    "id": 17,
    "items": [
      {
        "term": null,
        "match": null,
        "incorrect": [
          "Uyğunluğu müəyyən edin."
        ]
      },
      {
        "term": "Köks qəfəsinin inkişaf qüsurlarına aidolan deformasiya",
        "match": "«Qıfvari»",
        "incorrect": []
      },
      {
        "term": "Döş sümüyünün deformasiyalarına aid olan formalardan biri",
        "match": null,
        "incorrect": [
          "Yastı",
          "Qayıqvari",
          "Kifoz"
        ]
      }
    ]
  },
  {
    "id": 18,
    "items": [
      {
        "term": "Ağciyərlərin ən şox rast gəlinən parazitar sistləri",
        "match": "Exinikokk sisti",
        "incorrect": []
      },
      {
        "term": "Anadangəlmə ağciyər sistlərinə aiddir",
        "match": "Bronxogen sist",
        "incorrect": [
          "Enterosistoma",
          "Vilms şişi",
          "Dermoid sisti"
        ]
      }
    ]
  },
  {
    "id": 19,
    "items": [
      {
        "term": "Dölün qıdalanmasını təmin edən axacaq",
        "match": "Ductus omfaloentericus",
        "incorrect": []
      },
      {
        "term": "Dölün sidik axarı",
        "match": "Uraxus =-˃Ductus spermaticus",
        "incorrect": [
          "Rektovezikal fistul",
          "Volf cismi"
        ]
      }
    ]
  },
  {
    "id": 20,
    "items": [
      {
        "term": null,
        "match": null,
        "incorrect": [
          "Uyğunluğu müəyyən edin."
        ]
      },
      {
        "term": "Hipertrofik anadangəlmə pilorostenozun simptomu",
        "match": "«Fəvvarəvari»qusma",
        "incorrect": []
      },
      {
        "term": "Pilorospazm",
        "match": "Az miqdarda olan tez-tez qusma =-˃Qanlı qusma",
        "incorrect": [
          "Mərkəz məşəli qusma",
          "«Boş» qusma"
        ]
      }
    ]
  },
  {
    "id": 21,
    "items": [
      {
        "term": "Pilorostenozun müalicəsi",
        "match": "Frede-Ramşted əməliyyatı",
        "incorrect": []
      },
      {
        "term": "Pilorospazmın müalicəsi",
        "match": "Antispazmolitik müalicəsi",
        "incorrect": [
          "Biançi əməliyyatı",
          "Müalicə təələb etmir",
          "Dühamel əəməliyyatı"
        ]
      }
    ]
  },
  {
    "id": 22,
    "items": [
      {
        "term": "Embriogenezdə fırlanmanın ikinci mərhələsi pozularsa",
        "match": "Ledd sindromu",
        "incorrect": []
      },
      {
        "term": "Embriogenezdə fırlanmanın üçüncü mərhələsi pozularsa",
        "match": "«Daxili dəbəlik»",
        "incorrect": [
          "Embrional dəbəlik",
          "Littre dəbəliyi",
          "Diafraqmal dəbəlik"
        ]
      }
    ]
  },
  {
    "id": 23,
    "items": [
      {
        "term": null,
        "match": null,
        "incorrect": [
          "24.Uyğunluğu müəyyən edin."
        ]
      },
      {
        "term": "İnvaqinasiyanın diaqnostik rentgenolojı üsulu",
        "match": "İrriqoqrafiya",
        "incorrect": []
      },
      {
        "term": "Anusun və düz bağırsağın atreziyasının diaqnostik rentgenolojı üsulu :-",
        "match": "Vangenstin üsulu",
        "incorrect": [
          "Ekskretor uroqrafiya",
          "Fistuloqrafiya",
          "İzotop stintiqrafiya"
        ]
      }
    ]
  },
  {
    "id": 24,
    "items": [
      {
        "term": "Yemək borusu atreziyasının ilk klinik simptomu",
        "match": "Ağızdan və burundan köpüklü mayenin axması",
        "incorrect": []
      },
      {
        "term": "Yemək borusunun anadangəlmə stenozun klinik simptomu",
        "match": "Qida udulmasının çətinləçməsi",
        "incorrect": [
          "Çoxsaylı qusma",
          "«Fəvvarəvari» qusma",
          "Qanlı qusma"
        ]
      }
    ]
  },
  {
    "id": 25,
    "items": [
      {
        "term": "Bağırsaq invaqinasiyasının cərrahi müalicəsi",
        "match": "Dezinvaqinasiya",
        "incorrect": []
      },
      {
        "term": "Anusun atreziyasının cərrahi müalicəsi",
        "match": "Proktoplastika",
        "incorrect": [
          "İrriqoqrafiya",
          "Xeyloplastika",
          "Nissen əməliyyatı"
        ]
      }
    ]
  },
  {
    "id": 26,
    "items": [
      {
        "term": "Göbək ciyəsinin dəbəliyi",
        "match": "Omphalocele",
        "incorrect": []
      },
      {
        "term": "İnkişaf qüsuru nəticəsində qarin boşluğu üzvlərinin xaricə çıxması",
        "match": "(qışalarsız):- ˃Qastroşizis",
        "incorrect": [
          "Enterokistoma",
          "Mekkel divertikulu",
          "Sistosele"
        ]
      }
    ]
  },
  {
    "id": 27,
    "items": [
      {
        "term": "Ledd sindromu",
        "match": "Bağırsağın fırlanma prossesinin pozulması",
        "incorrect": []
      },
      {
        "term": "Mekonium keçməzliyi",
        "match": "Mədəaltı vəzin fibrokistozu",
        "incorrect": [
          "Bağırsağın rekanalizasiyasının pozulması",
          "Qarın boşluğunda bitişmələrin olması",
          "Mədəaltı vəzin üzükvari olması"
        ]
      }
    ]
  },
  {
    "id": 28,
    "items": [
      {
        "term": "Axalaziya",
        "match": "Kardial hissənin davamlı spazmı",
        "incorrect": []
      },
      {
        "term": "Xalaziya",
        "match": "Kardioezofaqial reflüksün olması",
        "incorrect": [
          "Yemək borusunun qisa olması",
          "Traxeyadan yemək borusuna fistulun olması",
          "Yemək borusunun daralması"
        ]
      }
    ]
  },
  {
    "id": 29,
    "items": [
      {
        "term": "Həqiqi diafraqma dəbəliyi",
        "match": "Qarın boşluğu orqanlarının yırtıq kisəsi daxilində döş boşluğuna daxil olması",
        "incorrect": []
      },
      {
        "term": "Yalançı diafraqma dəbəliyi",
        "match": "Yırtıq kisəsinin olmaması",
        "incorrect": [
          "Diafraqma gümbəzinin yüksəkdə yerləşməsi",
          "Divararalığının patoloji prosses tərəfə yerdəyişməsi",
          "Yemək borusu dəliyinin geniş olması"
        ]
      }
    ]
  },
  {
    "id": 30,
    "items": [
      {
        "term": "İnvaginasiya törədir",
        "match": "Peyerts-Egers sindromu",
        "incorrect": []
      },
      {
        "term": "Obturasiya törədir",
        "match": "Fito və trixobezoarlar",
        "incorrect": [
          "Daxili yırtıqlar",
          "Əməliyyatdan sonrakı bitişmələr",
          "Karoli xəstəliyi"
        ]
      }
    ]
  },
  {
    "id": 31,
    "items": [
      {
        "term": "Hipospadiya",
        "match": "Uretranın alt divarının olmaması",
        "incorrect": []
      },
      {
        "term": "Epispadiya",
        "match": "Uretranın ön divarının olmaması",
        "incorrect": [
          "Uretranın olmaması",
          "Ureterin atreziyası",
          "Sidik kisəsinin ön divarının olmaması"
        ]
      }
    ]
  },
  {
    "id": 32,
    "items": [
      {
        "term": "Diafraqma altında sərbəst qaz",
        "match": "Mədə xorasının deşilməsi",
        "incorrect": []
      },
      {
        "term": "Qarın boşluğunun yuxarı mərtəbəsində iki üfuqi maye səviyyəsi",
        "match": "12 barmaq bağırsaq keçməzliyi",
        "incorrect": [
          "Yoğun bağırsaq keçməzliyi",
          "Obturasion bağırsaq keçməzliyi",
          "Appendikulyar peritonit"
        ]
      }
    ]
  },
  {
    "id": 33,
    "items": [
      {
        "term": null,
        "match": null,
        "incorrect": [
          "39.Uyğunluğu müəyyən edin."
        ]
      },
      {
        "term": "Yemək borusunun atreziyası",
        "match": "Əlamətləri həyatın ilk saatından özünü biruzə verir",
        "incorrect": []
      },
      {
        "term": "Pilorostenoz",
        "match": "Əlamətləri əsasən həyatın 2-4-cü həftəsindən özünü biruzə verir",
        "incorrect": [
          "Simptomları həyatın 3-cü ayından sonra meydana çıxir",
          "Xəstəlik özünü 6 aydan sonra biruzə verir",
          "3-6 yaşlarda rast gəlinir"
        ]
      }
    ]
  },
  {
    "id": 34,
    "items": [
      {
        "term": "Yemək borusunun atreziyası",
        "match": "Yemək borusunun zondlanması",
        "incorrect": []
      },
      {
        "term": "Kardioezofagial reflüks",
        "match": "Yemək borusu mənfəzinin PH metriyası =-˃Kompüter tomoqrafiya",
        "incorrect": [
          "Döş qəfəsinin icmal rentgenoqrafiyası",
          "Bronxoqrafiya"
        ]
      }
    ]
  },
  {
    "id": 35,
    "items": [
      {
        "term": null,
        "match": null,
        "incorrect": [
          "41.Uyğunluğu müəyyən edin."
        ]
      },
      {
        "term": "Bronxektaziya",
        "match": "Bronxoqrafiya",
        "incorrect": []
      },
      {
        "term": "Piopnevmotoraks",
        "match": "Döş qəfəsinin icmal rentgenoqrafiyası",
        "incorrect": [
          "Mediastenoskopiya",
          "Yemək borusu mənfəzinin PH metriyası",
          "Yemək borusunun zondlanması"
        ]
      }
    ]
  },
  {
    "id": 36,
    "items": [
      {
        "term": null,
        "match": null,
        "incorrect": [
          "42.Uyğunluğu müəyyən edin."
        ]
      },
      {
        "term": "Yemək borusunun atreziyası",
        "match": "Ağızdan və burundan köpüklü ifrazatın xaric olması",
        "incorrect": []
      },
      {
        "term": "Traxeomalyasiya",
        "match": "Nəfəsvermə zamanı stidoroz tənəffüs",
        "incorrect": [
          "Döş qəfəsində asimmetriya",
          "Asimmetriya və qarının batıqlığı",
          "Amforik tənəffüs"
        ]
      }
    ]
  },
  {
    "id": 37,
    "items": [
      {
        "term": "Ağ ciyərin pay emfizeması",
        "match": "Döş qəfəsinin bir yarısının qabarması",
        "incorrect": []
      },
      {
        "term": "Diafraqma dəbəliyi",
        "match": "Asimmetriya və qarının batıqlıq olması",
        "incorrect": [
          "Pueril tənəffüs",
          "Nəfəsvermə zamanı stidoroz tənəffüs",
          "Amforik tənəffüs"
        ]
      }
    ]
  },
  {
    "id": 38,
    "items": [
      {
        "term": null,
        "match": null,
        "incorrect": [
          "Uyğunluğu müəyyən edin."
        ]
      },
      {
        "term": "Koloboma",
        "match": "Gözün iç bucağından üst dodağa qədər olan yarıq",
        "incorrect": []
      },
      {
        "term": "Makrostoma",
        "match": "Ağız bucağından qulaq seyvanına kimi uzanan yarıq",
        "incorrect": [
          "Üst dodağın yarığı",
          "Sərt damağın birləşməməsi",
          "Dilaltı yüyənin qısalığı"
        ]
      }
    ]
  },
  {
    "id": 39,
    "items": [
      {
        "term": null,
        "match": null,
        "incorrect": [
          "Uyğunluğu müəyyən edin."
        ]
      },
      {
        "term": "Üst dodağın yarığı(cərrahi müalicə)",
        "match": "Xeyloplastika",
        "incorrect": []
      },
      {
        "term": "Sərt damağın bitişməməsi(cərrahi müalicə)",
        "match": "Uranoplastika",
        "incorrect": [
          "Dermoplastika",
          "Osteoplastika",
          "Mioplastika"
        ]
      }
    ]
  },
  {
    "id": 40,
    "items": [
      {
        "term": null,
        "match": null,
        "incorrect": [
          "Uyğunluğu müəyyən edin."
        ]
      },
      {
        "term": "Mekkel divertikulunun fəsadları",
        "match": "Qanaxma, baqırsaq keçməzliyi",
        "incorrect": []
      },
      {
        "term": "Kəskin appendisitin fəsadları",
        "match": "Peritonit, infiltrat",
        "incorrect": [
          "Enterokolit, ishal",
          "Paraproktit, qanaxma",
          "Procesus vaqinalis(ın) obliterasiyaya uğramaması"
        ]
      }
    ]
  },
  {
    "id": 41,
    "items": [
      {
        "term": null,
        "match": null,
        "incorrect": [
          "Uyğunluğu müəyyən edin."
        ]
      },
      {
        "term": "Boynun orta sisti",
        "match": "Qalxanabənzər-dilaltı uğramaması axacağının obliterasiyaya",
        "incorrect": []
      },
      {
        "term": "Boynun yan sisti",
        "match": "Timus-udlaq axacağının obliterasiyaya uğramaması",
        "incorrect": [
          "Uraxusun obliterasiyaya uğramaması",
          "Ductus omfaloenterikus(un) obliterasiyaya uğramaması",
          "Procesus vaqinalis(ın) obliterasiyaya uğramaması"
        ]
      }
    ]
  },
  {
    "id": 42,
    "items": [
      {
        "term": null,
        "match": null,
        "incorrect": [
          "içərisində"
        ]
      },
      {
        "term": "Omphalocele",
        "match": "Yirtıq mötəviyyatı göbək ciyəsi qışaları yerləşir",
        "incorrect": []
      },
      {
        "term": "Qastroşizis",
        "match": "Anadangəlmə qarının ön divarının defektindən qarın boşluğu üzvlərinin xaricə çıxması omfaloenterikus(un) içərisində yerləşir qışaları",
        "incorrect": [
          "Yirtıq mötəviyyatı uraxusun içərisində yerləşir",
          "Yirtıq mötəviyyatı ductus",
          "Bağırsaq ilgəkleri procesus vaqinalis(ın) içərisində yerləşir"
        ]
      }
    ]
  },
  {
    "id": 43,
    "items": [
      {
        "term": null,
        "match": null,
        "incorrect": [
          "Uyğunluğu müəyyən edin."
        ]
      },
      {
        "term": "Omphalocelenin müalicəsi",
        "match": "Konservativ və cərrahi",
        "incorrect": []
      },
      {
        "term": "Qastroşizisinmüalicəsi",
        "match": "Yalnız cərrahi",
        "incorrect": [
          "Yalnız konservativ",
          "Müalicə tələb olunmur",
          "Ölü doğulur"
        ]
      }
    ]
  },
  {
    "id": 44,
    "items": [
      {
        "term": null,
        "match": null,
        "incorrect": [
          "Uyğunluğu müəyyən edin."
        ]
      },
      {
        "term": "Oğlanlarda qasıq yırtığının möhtəviyyatı",
        "match": "Nazik bağırsaq ilgəyi",
        "incorrect": []
      },
      {
        "term": "Qızlarda qasıq yırtığının möhtəviyyatı",
        "match": "Yumurtalıq",
        "incorrect": []
      },
      {
        "term": null,
        "match": "Uşaqlıq",
        "incorrect": [
          "Xaya",
          "İrinli maye",
          "Böyrək"
        ]
      }
    ]
  },
  {
    "id": 45,
    "items": [
      {
        "term": null,
        "match": null,
        "incorrect": [
          "Uyğunluğu müəyyən edin."
        ]
      },
      {
        "term": "Ginekomastiya",
        "match": "Oğlanlarda süd vəzinin böyük olması",
        "incorrect": []
      },
      {
        "term": "Polimastiya",
        "match": "Süd vəzilərinin sayının çox olması",
        "incorrect": []
      },
      {
        "term": null,
        "match": "Süd vəzinin olmaması",
        "incorrect": [
          "Qızlarda süd vəzinin böyük olması",
          "Süd vəzilərinin asimmetrik inkişafı",
          "Süd vəzi gilələrinin sayının çox olması"
        ]
      }
    ]
  },
  {
    "id": 46,
    "items": [
      {
        "term": "Ginekomastiya",
        "match": "Oğlanlarda süd vəzinin böyük olması",
        "incorrect": []
      },
      {
        "term": "Amastiya",
        "match": "Süd vəzilərinin olmaması",
        "incorrect": []
      },
      {
        "term": null,
        "match": "Oğlanlarda süd vəzinin sayının çox olması",
        "incorrect": [
          "Qızlarda süd vəzinin böyük olması",
          "Süd vəzilərinin asimmetrik inkişafı",
          "Süd vəzi gilələrinin sayının çox olması"
        ]
      }
    ]
  },
  {
    "id": 47,
    "items": [
      {
        "term": "Makrostomiya",
        "match": "Ağızın böyük olması",
        "incorrect": []
      },
      {
        "term": "Makroqlossiya",
        "match": "Dilin böyük olması",
        "incorrect": []
      },
      {
        "term": null,
        "match": "Üst dodağın böyük olması",
        "incorrect": [
          "Alt dodağın böyük olması",
          "Dodaqların böyük olması",
          "Dilin olmaması"
        ]
      }
    ]
  },
  {
    "id": 48,
    "items": [
      {
        "term": "Boynun orta fistulu müalicə olunur",
        "match": "Fistula yolu ilə dilaltı sümüyün cisminin rezeksiyası",
        "incorrect": []
      },
      {
        "term": "Boynun yan fistulu müalicə olunur",
        "match": "Fistula yolunun tam xaric edilməsi",
        "incorrect": []
      },
      {
        "term": null,
        "match": "Konservativ yol ilə",
        "incorrect": [
          "Fistula traktınınantiseptiklərlə işlənməsi ilə",
          "Heç bir müalicəyə ehtiyac yoxdur"
        ]
      }
    ]
  },
  {
    "id": 49,
    "items": [
      {
        "term": "Poliologiya",
        "match": "Süd vəzisi gilələrinin sayının çoxluğu",
        "incorrect": []
      },
      {
        "term": "Polimastiya",
        "match": "Süd vəzilərinin sayının çox olması",
        "incorrect": []
      },
      {
        "term": null,
        "match": "Süd vəzinin olmaması",
        "incorrect": [
          "Qızlarda süd vəzinin böyük olması",
          "Süd vəzilərinin asimmetrik inkişafı",
          "Süd vəzi gilələrinin olmaması"
        ]
      }
    ]
  },
  {
    "id": 50,
    "items": [
      {
        "term": "Mexaniki bağırsaq keçməzliyinə aiddir",
        "match": "Stranqulyasion, invaginasion, obturasion",
        "incorrect": []
      },
      {
        "term": "Dinamiki bağırsaq keçməzliyinə aiddir",
        "match": "Paralitik, spastik",
        "incorrect": []
      },
      {
        "term": null,
        "match": "Paralitik, invaginasion Uyğunluğu müəyyən edin.",
        "incorrect": [
          "Stranqulyasion, spastik",
          "Obturasion, paralitik, spastik",
          "İnvaginasion, paralitik, obturasion"
        ]
      }
    ]
  },
  {
    "id": 51,
    "items": [
      {
        "term": "Polidaktiliya",
        "match": "Barmaqların sayının çox olması",
        "incorrect": []
      },
      {
        "term": "Sindaktiliya",
        "match": "Barmaqların bitişik olması",
        "incorrect": []
      },
      {
        "term": null,
        "match": "Barmaqların uzun olması",
        "incorrect": [
          "Barmaqların qısa olması",
          "Barmaqların sayının az olması",
          "Barmaqların yana doğru əyilməsi"
        ]
      }
    ]
  },
  {
    "id": 52,
    "items": [
      {
        "term": "Piopnevmotoraks",
        "match": "Plevral boşluğa irin və havanın toplanması",
        "incorrect": []
      },
      {
        "term": "Pnevmotoraks",
        "match": "Plevral boşluqda havanın olması",
        "incorrect": []
      },
      {
        "term": null,
        "match": "Plevral boşluqda mayenin olması",
        "incorrect": [
          "Plevral boşluqda qanın olması",
          "Agciyərlərin kəskin havalanması",
          "Ağciyərlə plevra arasında bitişmələrin olması"
        ]
      }
    ]
  },
  {
    "id": 53,
    "items": [
      {
        "term": "Piotoraks",
        "match": "Plevral boşluqda irinin toplanması",
        "incorrect": []
      },
      {
        "term": "Hemotoraks",
        "match": "Plevral boşluqda qanın toplanması",
        "incorrect": []
      },
      {
        "term": null,
        "match": "Plevral boşluqda havanın olması",
        "incorrect": [
          "Plevral boşluqda mayenin toplanması",
          "Ağciyərlə plevra arasında bitişmələrin olması",
          "Agciyərlərin kəskin havalanması"
        ]
      }
    ]
  },
  {
    "id": 54,
    "items": [
      {
        "term": "Pnevmotoraks",
        "match": "Atmosfer havasının plevra boşluğuna keçməsi",
        "incorrect": []
      },
      {
        "term": "Hemotoraks",
        "match": "Qanın plevra boşluğuna axması",
        "incorrect": [
          "İrinin plevra boşluğuna yığılması",
          "Plevranın zədələnməsi",
          "Plevra boşluğunda abssesin yaranması"
        ]
      }
    ]
  },
  {
    "id": 55,
    "items": [
      {
        "term": "Açıq pnevmotoraks",
        "match": "Plevra boşluğu ilə xarici mühit arasında sərbəst əlaqə yarananda",
        "incorrect": []
      },
      {
        "term": "Qapalı pnevmotoraks",
        "match": "Nəfəs alarkən hava plevra boşluğuna daxil olur, nəfəs vermə zamanı isə qapaq rolunu oynayan toxuma yara defektini tutur və havanın xaric olmasına mane olur",
        "incorrect": [
          "Plevranın zədələnməsi",
          "İrinin və havanın plevra boşluğuna yığılması",
          "Qanın plevra boşluğuna yığılması"
        ]
      }
    ]
  },
  {
    "id": 56,
    "items": [
      {
        "term": "Nazik və yoğun bağırsaqların polipozu",
        "match": "Peyts-Egers sindromu",
        "incorrect": []
      },
      {
        "term": "Üzün anadangəlmə inkişaf güsuru",
        "match": "Per-Roben sindromu",
        "incorrect": [
          "Marfan sindromu",
          "Osqut-Şlatter xəstəliyi",
          "Koxa Vara"
        ]
      }
    ]
  },
  {
    "id": 57,
    "items": [
      {
        "term": "Soxulcanabənzər çıxıntının qarın boşluğunda yerləşmə variantı",
        "match": "Canaq formalı",
        "incorrect": []
      },
      {
        "term": "Kəskin appendisitin formalardan biri",
        "match": "Fleqmanoz",
        "incorrect": [
          "Retrosternal",
          "Kalkulyoz",
          "Çapıq formalı"
        ]
      }
    ]
  },
  {
    "id": 58,
    "items": [
      {
        "term": "Appendikulyar infiltratın I mərhələdə müalicəsi",
        "match": "Konservativ müalicə",
        "incorrect": []
      },
      {
        "term": "Kəskin fleqmanozappendisitinin müalicəsi",
        "match": "Cərrahi əməliyyat",
        "incorrect": [
          "Dinamiki müşahidə",
          "Müalicə tələb olunmur",
          "Bülau üsulu ilə drenaj"
        ]
      }
    ]
  },
  {
    "id": 59,
    "items": [
      {
        "term": "Bronxoektaziya xəstəliyinin mənşəyinə görə təsnifatı",
        "match": "Anadangəlmə, dizontogenik, qazanılma",
        "incorrect": []
      },
      {
        "term": "Bronxoektaziya",
        "match": "dairəvi,sistəbənzər xəstəliyinin formasına görə təsnifatı:->Silindirvari, 85. Uyğunluğu müəyyən edin. {",
        "incorrect": [
          "Adinamik, septikopiemik, yerli",
          "Ageneziya, aplaziya, hipoplaziya",
          "Kəskinləşmə, remissiya"
        ]
      },
      {
        "term": "Ureterosele",
        "match": "Sidik axarının intramural hissəsinin sistoz formada genişlənməsi.",
        "incorrect": []
      },
      {
        "term": "Meqaureter",
        "match": "Sidik axarının total genişlənməsi. yerində olmaması =-> Sidik kanalının ön divarının tam və ya natamam deffekti. 86. { Uyğunluğu müəyyən edin.",
        "incorrect": [
          "Uretranın distal hissəsinin deffekti nəticəsində xarici dəliyin",
          "Sidik axarının retrokaval yerləşməsi"
        ]
      },
      {
        "term": "Yemək borusunun atreziyası zamanı radikal əməliyyat",
        "match": "Birmomenli anastomoz",
        "incorrect": []
      },
      {
        "term": "Yemək borusunun atreziyası zamanı paliativ əməliyyat",
        "match": "İkili ezofaqostomiya",
        "incorrect": [
          "Uc-yana anastomoz",
          "Vinkelman əməliyyatı",
          "Ezofaqoskopiya"
        ]
      }
    ]
  },
  {
    "id": 60,
    "items": [
      {
        "term": null,
        "match": null,
        "incorrect": [
          "Uyğunluğu müəyyən edin."
        ]
      },
      {
        "term": "Boyunun sistoz limfangiomasının mualicəsi",
        "match": "Sistin punksiyası və bleomisin",
        "incorrect": []
      },
      {
        "term": "Boyunun hemangiomasının müalicəsi",
        "match": "Propranolol preparatı ilə mualicə",
        "incorrect": [
          "Sistin punksiyası",
          "Antibiotikoterapiya",
          "Sistin marsupilizasiyası"
        ]
      }
    ]
  }
]
